<?xml version="1.0" encoding="UTF-8"?>
<file name="./outputFiles/xml/Chant21/Hins1883Chant21NomsCoupe.xml">
  <ID1 text="^" lemma="^" tag="^" />
  <ID2 text="" lemma="" tag="" />
  <ID3 text="" lemma="" tag="" />
  <ID4 text="Pénélope détacha du clou l' arc avec l' étui brillant qui l' entourait ; puis s' étant assise , elle retira l' arc du roi et l' ayant placé sur ses genoux , pleura abondamment " lemma="Penelope detacher du clou le arc avec le etui brillant qui le entourer ; puis se etre asseoir , elle retirer le arc du roi et le avoir placer sur ses genou , pleurer abondamment " tag="NAM VER DET:ART NOM DET:ART NOM PRP DET:ART NOM ADJ PRO DET:ART VER:pper PUN ADV PRO VER VER PUN PRO VER DET:ART NOM DET:ART NOM CONJcoord DET:ART VER VER:pper PRP DET:ART NOM PUN VER ADV " />
  <ID5 text="Lorsqu' elle se fut soulagée en versant des larmes abondantes , elle se dirigea vers la salle où se trouvaient les illustres prétendants , ayant en mains l' arc détendu et le carquois , dans lequel se trouvaient beaucoup de flèches meurtrières " lemma="lorsque elle se etre soulager en versant un larme abondant , elle se diriger vers le salle ou se trouver le illustre pretendant , avoir en main le arc detendu et le carquois , dans lequel se trouver beaucoup de fleche meurtrier " tag="CONJsubord PRO PRO VER VER:pper PRP NOM DET:ART NOM ADJ PUN PRO PRO VER PRP DET:ART NOM PRO PRO VER DET:ART ADJ NOM PUN VER PRP NOM DET:ART NOM ADJ CONJcoord DET:ART NOM PUN PRP PRO PRO VER ADV PRP NOM ADJ " />
  <ID6 text="Derrière elle , les suivantes portaient un coffre où se trouvaient beaucoup d' objets en fer et en airain , qu' " lemma="derriere elle , le suivant porter un coffre ou se trouver beaucoup de objet en fer et en airain , que " tag="PRP PRO PUN DET:ART ADJ VER:pper DET:ART NOM PRO PRO VER ADV PRP NOM PRP NOM CONJcoord PRP NOM PUN PRO " />
  <ID7 text="^" lemma="^" tag="^" />
  <ID8 text="Ulysse avait gagnés dans les jeux " lemma="Ulysse avoir gagner dans le jeu " tag="NAM VER VER:pper PRP DET:ART NOM " />
  <ID9 text="^" lemma="^" tag="^" />
  <ID10 text="/ Lorsque la noble femme arriva près des prétendants , elle s' arrêta à la porte de la salle bien construite , ayant devant ses joues un voile brillant " lemma="/ lorsque le noble femme arriver pres un pretendant , elle se arreter a le porte de le salle bien construire , avoir devant ses joue un voile brillant " tag="PUN CONJsubord DET:ART ADJ NOM VER PRP DET:ART NOM PUN PRO PRO VER PRP DET:ART NOM PRP DET:ART NOM ADV VER PUN VER PRP DET:ART NOM DET:ART NOM ADJ " />
  <ID11 text="^" lemma="^" tag="^" />
  <ID12 text="^" lemma="^" tag="^" />
  <ID13 text="^" lemma="^" tag="^" />
  <ID14 text="^" lemma="^" tag="^" />
  <ID15 text="^" lemma="^" tag="^" />
  <ID16 text="^" lemma="^" tag="^" />
  <ID17 text="S' adressant aux prétendants , elle leur dit aussitôt " lemma="se adresser aux pretendant , elle leurs dire aussitôt " tag="PRO VER DET:ART NOM PUN PRO DET:ART VER ADV " />
  <ID18 text="^" lemma="^" tag="^" />
  <ID19 text="^" lemma="^" tag="^" />
  <ID20 text="/ &quot; Écoutez moi , audacieux prétendants , qui , mangeant et buvant continuellement , ruinez la maison d' un homme absent depuis longtemps " lemma="/ &quot; ecouter moi , audacieux pretendant , qui , manger et boire continuellement , ruiner le maison de un homme absent depuis longtemps " tag="PUN PUN VER PRO PUN ADJ NOM PUN PRO PUN VER CONJcoord VER ADV PUN VER DET:ART NOM PRP DET:ART NOM ADJ PRP ADV " />
  <ID21 text="^" lemma="^" tag="^" />
  <ID22 text="^" lemma="^" tag="^" />
  <ID23 text="Vous n' avez pu trouver d' autre prétexte que de dire que vous venez pour me marier et faire de moi votre femme " lemma="vous ne avoir pouvoir trouver de autre pretexte que de dire que vous venir pour me marier et faire de moi votre femme " tag="PRO ADV VER VER VER PRP ADJ NOM PRO PRP VER PRO PRO VER PRP PRO VER CONJcoord VER PRP PRO DET:ART NOM " />
  <ID24 text="^" lemma="^" tag="^" />
  <ID25 text="^" lemma="^" tag="^" />
  <ID26 text="^" lemma="^" tag="^" />
  <ID27 text="^" lemma="^" tag="^" />
  <ID28 text="Eh " lemma="he " tag="EXCL " />
  <ID29 text="^" lemma="^" tag="^" />
  <ID30 text="^" lemma="^" tag="^" />
  <ID31 text="bien , voyons , ô prétendants , voilà l' épreuve qui s' offre à vous " lemma="bien , voir , ô pretendant , voila le epreuve qui se offrir a vous " tag="ADV PUN VER PUN EXCL NOM PUN PRP DET:ART NOM PRO PRO VER PRP PRO " />
  <ID32 text="^" lemma="^" tag="^" />
  <ID33 text="Je vous apporte le grand arc du divin " lemma="je vous apporter le grand arc du divin " tag="PRO PRO VER DET:ART ADJ NOM DET:ART ADJ " />
  <ID34 text="^" lemma="^" tag="^" />
  <ID35 text="^" lemma="^" tag="^" />
  <ID36 text="^" lemma="^" tag="^" />
  <ID37 text="Ulysse ; celui qui tendra le plus facilement l' arc de ses mains , et lancera une flèche à travers les ouvertures de toutes les douze haches , celui là je le suivrai , abandonnant cette maison conjugale , si belle , pleine de tout ce qui est nécessaire à la vie " lemma="Ulysse ; celui qui tendre le plus facilement le arc de ses main , et lancer un fleche a travers le ouverture de tout le douze hache , celui la je le suivre , abandonner cette maison conjugal , si beau , plein de tout ce qui etre necessaire a le vie " tag="NAM PUN PRO PRO ADJ DET:ART ADV ADV DET:ART NOM PRP DET:ART NOM PUN CONJcoord VER DET:ART NOM PRP NOM DET:ART NOM PRP DET:ART DET:ART NUM NOM PUN PRO ADV PRO DET:ART VER PUN VER:pper DET:ART NOM ADJ PUN CONJsubord ADJ PUN ADJ PRP DET:ART DET:ART PRO VER ADJ PRP DET:ART NOM " />
  <ID38 text="^" lemma="^" tag="^" />
  <ID39 text="^" lemma="^" tag="^" />
  <ID40 text="^" lemma="^" tag="^" />
  <ID41 text="^" lemma="^" tag="^" />
  <ID42 text="je crois que je m' en souviendrai toujours , même dans mes songes " lemma="je croire que je me en souvenir toujours , meme dans mes songe " tag="PRO VER PRO PRO PRO PRP VER ADV PUN ADV PRP DET:ART NOM " />
  <ID43 text="^" lemma="^" tag="^" />
  <ID44 text="^" lemma="^" tag="^" />
  <ID45 text="^" lemma="^" tag="^" />
  <ID46 text="^" lemma="^" tag="^" />
  <ID47 text="^" lemma="^" tag="^" />
  <ID48 text="^" lemma="^" tag="^" />
  <ID49 text="^" lemma="^" tag="^" />
  <ID50 text="^" lemma="^" tag="^" />
  <ID51 text="^" lemma="^" tag="^" />
  <ID52 text="^" lemma="^" tag="^" />
  <ID53 text="&quot; / Elle parla ainsi et ordonna à " lemma="&quot; / elle parler ainsi et ordonner a " tag="PUN PUN PRO VER ADV CONJcoord VER PRP " />
  <ID54 text="^" lemma="^" tag="^" />
  <ID55 text="Eumée , le divin porcher , de remettre aux prétendants l' arc et le fer poli " lemma="Eumee , le divin porcher , de remettre aux pretendant le arc et le fer poli " tag="NAM PUN DET:ART ADJ NOM PUN PRP VER DET:ART NOM DET:ART NOM CONJcoord DET:ART NOM ADJ " />
  <ID56 text="" lemma="" tag="" />
  <ID57 text="Eumée les reçut et les remit en pleurant " lemma="Eumee le recevoir et le remettre en pleurer " tag="NAM DET:ART VER CONJcoord DET:ART VER PRP VER " />
  <ID58 text="^" lemma="^" tag="^" />
  <ID59 text="Le bouvier " lemma="le bouvier " tag="DET:ART NOM " />
  <ID60 text="^" lemma="^" tag="^" />
  <ID61 text="Philétios , qui l' accompagnait , pleura aussi , en voyant l' arc de son maître " lemma="Philetios , qui le accompagner , pleurer aussi , en voir le arc de son maître " tag="NAM PUN PRO DET:ART VER PUN VER ADV PUN PRP VER DET:ART NOM PRP DET:ART NOM " />
  <ID62 text="^" lemma="^" tag="^" />
  <ID63 text="/ Alors le fort " lemma="/ alors le fort " tag="PUN ADV DET:ART ADV " />
  <ID64 text="Télémaque dit " lemma="Telemaque dire " tag="NAM VER " />
  <ID65 text="/ &quot; Hélas " lemma="/ &quot; helas " tag="PUN PUN EXCL " />
  <ID66 text="" lemma="" tag="" />
  <ID67 text="Zeus , fils de " lemma="Zeus , fils de " tag="NAM PUN NOM PRP " />
  <ID68 text="Cronos , m' a donc rendu insensé " lemma="Cronos , me avoir donc rendre insense " tag="NAM PUN PRO VER CONJcoord VER ADJ " />
  <ID69 text="ma chère mère , toute sage qu' elle est , dit qu' abandonnant cette maison , elle va suivre un autre homme , et cependant je ris et me réjouis dans mon cœur insensé " lemma="ma cher mere , tout sage que elle etre , dire que abandonner cette maison , elle aller suivre un autre homme , et cependant je rire et me rejouir dans mon coeur insense " tag="DET:ART ADJ NOM PUN DET:ART ADJ PRO PRO VER PUN VER PRO VER:pper DET:ART NOM PUN PRO VER VER DET:ART ADJ NOM PUN CONJcoord ADV PRO VER CONJcoord PRO VER PRP DET:ART NOM ADJ " />
  <ID70 text="^" lemma="^" tag="^" />
  <ID71 text="Mais courage , prétendants , puisque le prix de la lutte est une femme comme il n' y en a pas d' autre dans la terre d' " lemma="mais courage , pretendant , puisque le prix de le lutte etre un femme comme il ne y en avoir pas de autre dans le terre de " tag="CONJcoord NOM PUN NOM PUN CONJsubord DET:ART NOM PRP DET:ART NOM VER DET:ART NOM CONJsubord PRO ADV PRO PRP VER ADV PRP ADJ PRP DET:ART NOM PRP " />
  <ID72 text="^" lemma="^" tag="^" />
  <ID73 text="^" lemma="^" tag="^" />
  <ID74 text="^" lemma="^" tag="^" />
  <ID75 text="Achaïe , ni dans la sainte " lemma="Achaïe , ni dans le saint " tag="NAM PUN CONJcoord PRP DET:ART ADJ " />
  <ID76 text="Pylos , ni à " lemma="Pylos , ni a " tag="NAM PUN CONJcoord PRP " />
  <ID77 text="Argos , ni à " lemma="Argos , ni a " tag="NAM PUN CONJcoord PRP " />
  <ID78 text="Mycènes " lemma="Mycenes " tag="NAM " />
  <ID79 text="du reste , vous le savez vous-mêmes ; qu' ai je besoin de faire l' éloge de ma mère " lemma="du rester , vous le savoir vous-memes ; que avoir je besoin de faire le eloge de ma mere " tag="DET:ART VER PUN PRO DET:ART VER PRO PUN PRO VER PRO NOM PRP VER DET:ART NOM PRP DET:ART NOM " />
  <ID80 text="Mais ne traînez pas l' affaire en longueur sous divers prétextes , ne tardez pas longtemps à tendre l' arc , afin que nous sachions qui l' emportera " lemma="mais ne traîner pas le affaire en longueur sous divers pretexte , ne tarder pas longtemps a tendre le arc , afin que nous savoir qui le emporter " tag="CONJcoord ADV VER ADV DET:ART NOM PRP NOM PRP ADJ NOM PUN ADV VER ADV ADV PRP ADJ DET:ART NOM PUN PRP PRO PRO VER PRO DET:ART VER " />
  <ID81 text="Moi-même , je veux tenter l' épreuve " lemma="moi-meme , je vouloir tenter le epreuve " tag="PRO PUN PRO VER VER DET:ART NOM " />
  <ID82 text="si je tends l' arc et fais passer ma flèche à travers les haches , ma respectable mère ne quittera pas , à ma grande douleur , cette maison pour suivre un autre homme , me laissant derrière elle seul possesseur des choses précieuses remportées en prix par mon père " lemma="si je tendre le arc et faire passer ma fleche a travers le hache , ma respectable mere ne quitter pas , a ma grand douleur , cette maison pour suivre un autre homme , me laisser derriere elle seul possesseur un chose precieux remporter en prix par mon pere " tag="CONJsubord PRO ADJ DET:ART NOM CONJcoord VER VER DET:ART NOM PRP NOM DET:ART NOM PUN DET:ART ADJ NOM ADV VER ADV PUN PRP DET:ART ADJ NOM PUN DET:ART NOM PRP VER DET:ART ADJ NOM PUN PRO VER PRP PRO ADJ NOM DET:ART NOM ADJ VER:pper PRP NOM PRP DET:ART NOM " />
  <ID83 text="&quot; / Il dit et s' étant levé brusquement , il rejeta de ses épaules son manteau de pourpre et en ôta son glaive acéré " lemma="&quot; / il dire et se etre lever brusquement , il rejeter de ses epaule son manteau de pourpre et en ôter son glaive acere " tag="PUN PUN PRO VER CONJcoord PRO VER VER ADV PUN PRO VER PRP DET:ART NOM DET:ART NOM PRP ADJ CONJcoord PRP VER DET:ART NOM ADJ " />
  <ID84 text="D' abord , ayant creusé un sillon , il y plaça les haches , toutes de même hauteur , les alignant au cordeau , puis il battit la terre tout autour " lemma="de abord , avoir creuser un sillon , il y placer le hache , tout de meme hauteur , le aligner au cordeau , puis il battre le terre tout autour " tag="PRP NOM PUN VER VER:pper DET:ART NOM PUN PRO PRO VER:pper DET:ART NOM PUN DET:ART PRP ADV NOM PUN DET:ART VER DET:ART NOM PUN ADV PRO VER DET:ART NOM DET:ART ADV " />
  <ID85 text="Tout le monde fut saisi d' étonnement , en voyant avec quel art il les avait placées , sans avoir , auparavant , jamais rien vu de pareil " lemma="tout le monde etre saisir de etonnement , en voir avec quel art il le avoir placer , sans avoir , auparavant , jamais rien voir de pareil " tag="DET:ART DET:ART NOM VER VER PRP NOM PUN PRP VER PRP DETinter NOM PRO DET:ART VER VER:pper PUN PRP VER PUN ADV PUN ADV PRO VER PRP ADJ " />
  <ID86 text="Ensuite , allant vers le seuil , il s' y tint debout et éprouva l' arc " lemma="ensuite , aller vers le seuil , il se y tenir debout et eprouver le arc " tag="ADV PUN VER PRP DET:ART NOM PUN PRO PRO PRO VER ADJ CONJcoord VER DET:ART NOM " />
  <ID87 text="Trois fois il l' ébranla , désirant le tendre ; trois fois il relâcha sa force , espérant toujours dans son cœur qu' il tendrait la corde et traverserait de sa flèche le fer " lemma="trois fois il le ebranler , desirer le tendre ; trois fois il relacher sa force , esperer toujours dans son coeur que il tendre le corde et traverser de sa fleche le fer " tag="NUM NOM PRO DET:ART VER PUN VER DET:ART ADJ PUN NUM NOM PRO VER DET:ART NOM PUN VER ADV PRP DET:ART NOM PRO PRO ADJ DET:ART NOM CONJcoord VER PRP DET:ART NOM DET:ART NOM " />
  <ID88 text="Et probablement il l' eût tendue au quatrième effort , mais " lemma="et probablement il le avoir tendu au quatrieme effort , mais " tag="CONJcoord ADV PRO DET:ART VER ADJ DET:ART ADJ NOM PUN CONJcoord " />
  <ID89 text="Ulysse le lui défendit d' un signe de tête et le retint malgré son désir " lemma="Ulysse le lui defendre de un signe de tete et le retenir malgre son desir " tag="NAM DET:ART PRO VER PRP DET:ART NOM PRP NOM CONJcoord DET:ART VER PRP DET:ART NOM " />
  <ID90 text="Alors le fort " lemma="alors le fort " tag="ADV DET:ART ADV " />
  <ID91 text="Télémaque dit " lemma="Telemaque dire " tag="NAM VER " />
  <ID92 text="/ &quot; Hélas , serai je toujours sans énergie et sans force , ou bien suis je encore trop jeune et ne puis je encore me fier à mes bras pour me défendre contre un homme qui m' attaquerait " lemma="/ &quot; helas , etre je toujours sans energie et sans force , ou bien etre je encore trop jeune et ne puis je encore me fier a mes bras pour me defendre contre un homme qui me attaquer " tag="PUN PUN EXCL PUN VER PRO ADV PRP NOM CONJcoord PRP NOM PUN PRO ADV VER PRO ADV ADV ADJ CONJcoord ADV ADV PRO ADV PRO ADJ PRP DET:ART NOM PRP PRO VER PRP DET:ART NOM PRO PRO VER " />
  <ID93 text="Mais voyons , vous qui l' emportez en force sur moi , essayez l' arc et terminons la lutte  / En parlant ainsi , il déposa l' arc à terre , l' appuyant contre les battants bien construits et bien polis de la porte  Quant au trait rapide , il l' appuya contre le bel anneau de la porte " lemma="mais voir , vous qui le emporter en force sur moi , essayer le arc et terminer le lutte  / en parler ainsi , il deposer le arc a terre , le appuyer contre le battant bien construire et bien poli de le porte  quant au trait rapide , il le appuyer contre le beau anneau de le porte " tag="CONJcoord VER PUN PRO PRO DET:ART VER PRP NOM PRP PRO PUN VER DET:ART NOM CONJcoord VER DET:ART NOM  PUN PRP VER ADV PUN PRO VER DET:ART NOM PRP NOM PUN DET:ART VER PRP DET:ART NOM ADV VER CONJcoord ADV ADJ PRP DET:ART NOM  NOM DET:ART NOM ADJ PUN PRO DET:ART VER PRP DET:ART ADJ NOM PRP DET:ART NOM " />
  <ID94 text="Lui-même se rassit sur le fauteuil d' où il s' était levé " lemma="lui-meme se rasseoir sur le fauteuil de ou il se etre lever " tag="PRO PRO VER PRP DET:ART NOM PRP PRO PRO PRO VER VER " />
  <ID95 text="Alors " lemma="alors " tag="ADV " />
  <ID96 text="Antinoos , fils d' " lemma="Antinoos , fils de " tag="NAM PUN NOM PRP " />
  <ID97 text="Eupithès , dit " lemma="Eupithes , dire " tag="NAM PUN VER " />
  <ID98 text="^" lemma="^" tag="^" />
  <ID99 text="/ &quot; Levez vous tous , compagnons , à tour de rôle en commençant par la droite , par le côté d' où l' on commence à verser le vin &quot; " lemma="/ &quot; lever vous tous , compagnon , a tour de rôle en commencer par le droite , par le côte de ou le on commencer a verser le vin &quot; " tag="PUN PUN VER PRO DET:ART PUN NOM PUN PRP NOM PRP NOM PRP VER PRP DET:ART NOM PUN PRP DET:ART NOM PRP PRO DET:ART PRO VER PRP VER DET:ART NOM PUN " />
  <ID100 text="/ Ainsi parla " lemma="/ ainsi parler " tag="PUN ADV VER " />
  <ID101 text="Antinoos et l' avis leur plut " lemma="Antinoos et le avis leurs plaire " tag="NAM CONJcoord DET:ART NOM DET:ART VER " />
  <ID102 text="" lemma="" tag="" />
  <ID103 text="Liodès , fils d' " lemma="Liodes , fils de " tag="NAM PUN NOM PRP " />
  <ID104 text="^" lemma="^" tag="^" />
  <ID105 text="^" lemma="^" tag="^" />
  <ID106 text="^" lemma="^" tag="^" />
  <ID107 text="^" lemma="^" tag="^" />
  <ID108 text="^" lemma="^" tag="^" />
  <ID109 text="Oenops , se leva le premier " lemma="Oenops , se lever le premier " tag="NAM PUN PRO VER DET:ART ADJ " />
  <ID110 text="C' était leur sacrificateur qui était toujours assis le plus près du beau cratère " lemma="ce etre leurs sacrificateur qui etre toujours asseoir le plus pres du beau cratere " tag="DET:ART VER DET:ART NOM PRO VER ADV VER DET:ART ADV PRP DET:ART ADJ NOM " />
  <ID111 text="lui seul était ennemi de l' injustice et il faisait des reproches à tous les prétendants ; ce fut lui qui le premier prit l' arc et le trait rapide " lemma="lui seul etre ennemi de le injustice et il faire un reproche a tous le pretendant ; ce etre lui qui le premier prendre le arc et le trait rapide " tag="PRO ADJ VER NOM PRP DET:ART NOM CONJcoord PRO VER DET:ART NOM PRP DET:ART DET:ART NOM PUN DET:ART VER PRO PRO DET:ART ADJ VER DET:ART NOM CONJcoord DET:ART NOM ADJ " />
  <ID112 text="Allant vers le seuil , il s' y tient debout et essaie l' arc ; mais il ne le tend pas , car ses mains molles et délicates sont bientôt fatiguées " lemma="aller vers le seuil , il se y tenir debout et essayer le arc ; mais il ne le tendre pas , car ses main mou et delicat etre bientôt fatigue " tag="VER PRP DET:ART NOM PUN PRO PRO PRO VER ADJ CONJcoord VER DET:ART NOM PUN CONJcoord PRO ADV DET:ART ADJ ADV PUN CONJcoord DET:ART NOM ADJ CONJcoord ADJ VER ADV ADJ " />
  <ID113 text="^" lemma="^" tag="^" />
  <ID114 text="^" lemma="^" tag="^" />
  <ID115 text="^" lemma="^" tag="^" />
  <ID116 text="^" lemma="^" tag="^" />
  <ID117 text="^" lemma="^" tag="^" />
  <ID118 text="^" lemma="^" tag="^" />
  <ID119 text="^" lemma="^" tag="^" />
  <ID120 text="^" lemma="^" tag="^" />
  <ID121 text="^" lemma="^" tag="^" />
  <ID122 text="Alors , il dit aux prétendants " lemma="alors , il dire aux pretendant " tag="ADV PUN PRO VER DET:ART NOM " />
  <ID123 text="^" lemma="^" tag="^" />
  <ID124 text="^" lemma="^" tag="^" />
  <ID125 text="/ &quot; Amis , puisque je ne le tends pas , qu' un autre le prenne " lemma="/ &quot; ami , puisque je ne le tendre pas , que un autre le prendre " tag="PUN PUN NOM PUN CONJsubord PRO ADV DET:ART ADJ ADV PUN PRO DET:ART ADJ DET:ART VER " />
  <ID126 text="^" lemma="^" tag="^" />
  <ID127 text="^" lemma="^" tag="^" />
  <ID128 text="En vérité cet arc privera de la pensée et du souffle beaucoup de héros , car il vaut beaucoup mieux mourir que de vivre sans obtenir ce pourquoi nous nous réunissons toujours ici , attendant tous les jours " lemma="en verite cet arc priver de le pensee et du souffle beaucoup de heros , car il valoir beaucoup mieux mourir que de vivre sans obtenir ce pourquoi nous nous reunir toujours ici , attendre tous le jour " tag="PRP NOM DET:ART NOM VER PRP DET:ART NOM CONJcoord DET:ART NOM ADV PRP NOM PUN CONJcoord PRO VER ADV ADV VER PRO PRP VER PRP VER DET:ART ADV PRO PRO VER ADV ADV PUN VER DET:ART DET:ART NOM " />
  <ID129 text="Maintenant chacun espère et médite en son esprit de marier " lemma="maintenant chacun esperer et mediter en son esprit de marier " tag="ADV PRO VER CONJcoord VER PRP DET:ART NOM PRP VER " />
  <ID130 text="^" lemma="^" tag="^" />
  <ID131 text="Pénélope , l' épouse d' " lemma="Penelope , le epoux de " tag="NAM PUN DET:ART NOM PRP " />
  <ID132 text="Ulysse " lemma="Ulysse " tag="NAM " />
  <ID133 text="^" lemma="^" tag="^" />
  <ID134 text="^" lemma="^" tag="^" />
  <ID135 text="^" lemma="^" tag="^" />
  <ID136 text="^" lemma="^" tag="^" />
  <ID137 text="Mais quand il aura éprouvé et connu l' arc , qu' il se fiance , en lui offrant des présents , à quelque autre des " lemma="mais quand il avoir eprouver et connaître le arc , que il se fiancer , en lui offrir un present , a quelque autre un " tag="CONJcoord CONJsubord PRO VER VER CONJcoord VER DET:ART NOM PUN PRO PRO PRO VER PUN PRP PRO VER DET:ART ADJ PUN PRP DET:ART ADJ DET:ART " />
  <ID138 text="^" lemma="^" tag="^" />
  <ID139 text="Achéennes au beau voile " lemma="Acheennes au beau voile " tag="NAM DET:ART ADJ NOM " />
  <ID140 text="Quant à " lemma="quant a " tag="NOM PRP " />
  <ID141 text="Pénélope , qu' elle se marie à celui qui lui / " lemma="Penelope , que elle se marier a celui qui lui / " tag="NAM PUN PRO PRO PRO VER PRP PRO PRO PRO PUN " />
  <ID142 text="Antinoos parla ainsi , l' interpellant par son nom " lemma="Antinoos parler ainsi , le interpeller par son nom " tag="NAM VER ADV PUN DET:ART VER PRP DET:ART NOM " />
  <ID143 text="/ &quot; " lemma="/ &quot; " tag="PUN PUN " />
  <ID144 text="^" lemma="^" tag="^" />
  <ID145 text="Liodès , quel discours terrible et dur s' est échappé de l' enceinte de tes dents " lemma="Liodes , quel discours terrible et dur se etre echapper de le enceinte de tes dent " tag="NAM PUN DETinter NOM ADJ CONJcoord ADJ PRO VER VER:pper PRP DET:ART ADJ PRP DET:ART NOM " />
  <ID146 text="^" lemma="^" tag="^" />
  <ID147 text="^" lemma="^" tag="^" />
  <ID148 text="Je suis indigné de l' entendre " lemma="je etre indigner de le entendre " tag="PRO VER VER:pper PRP DET:ART VER " />
  <ID149 text="Quoi " lemma="quoi " tag="PRO " />
  <ID150 text="cet arc privera de la pensée et du souffle beaucoup de héros , parce que tu ne peux pas le tendre " lemma="cet arc priver de le pensee et du souffle beaucoup de heros , parce que tu ne pouvoir pas le tendre " tag="DET:ART NOM VER PRP DET:ART NOM CONJcoord DET:ART NOM ADV PRP NOM PUN Indef PRO PRO ADV VER ADV DET:ART ADJ " />
  <ID151 text="C' est que ta respectable mère ne t' a pas engendré pour être un tendeur d' arc et de flèches ; mais bientôt les autres prétendants illustres le tendront " lemma="ce etre que ta respectable mere ne tu avoir pas engendrer pour etre un tendeur de arc et de fleche ; mais bientôt le autres pretendant illustre le tendre " tag="DET:ART VER PRO DET:ART ADJ NOM ADV PRO VER ADV VER:pper PRP VER DET:ART NOM PRP NOM CONJcoord PRP NOM PUN CONJcoord ADV DET:ART PRO NOM ADJ DET:ART ADJ " />
  <ID152 text="^" lemma="^" tag="^" />
  <ID153 text="&quot; / Il parla ainsi et ordonna à " lemma="&quot; / il parler ainsi et ordonner a " tag="PUN PUN PRO VER ADV CONJcoord VER PRP " />
  <ID154 text="Mélanthios , le chevrier " lemma="Melanthios , le chevrier " tag="NAM PUN DET:ART NOM " />
  <ID155 text="^" lemma="^" tag="^" />
  <ID156 text="^" lemma="^" tag="^" />
  <ID157 text="/ &quot; Allons , allume du feu dans la salle , " lemma="/ &quot; aller , allumer du feu dans le salle , " tag="PUN PUN VER PUN VER DET:ART NOM PRP DET:ART NOM PUN " />
  <ID158 text="Mélanthios , place auprès un grand siège et une toison dessus et apporte du dedans un grand rouleau de suif , afin que , réchauffant l' arc et le frottant de suif , nous l' éprouvions et terminions la lutte " lemma="Melanthios , place aupres un grand siege et un toison dessus et apporter du dedans un grand rouleau de suif , afin que , rechauffer le arc et le frotter de suif , nous le eprouver et terminer le lutte " tag="NAM PUN NOM PRP DET:ART ADJ NOM CONJcoord DET:ART NOM ADV CONJcoord VER DET:ART ADV DET:ART ADJ NOM PRP NOM PUN PRP PRO PUN VER:pper DET:ART NOM CONJcoord DET:ART VER PRP NOM PUN PRO DET:ART VER CONJcoord VER DET:ART NOM " />
  <ID159 text="^" lemma="^" tag="^" />
  <ID160 text="&quot; / Il parla ainsi ; aussitôt " lemma="&quot; / il parler ainsi ; aussitôt " tag="PUN PUN PRO VER ADV PUN ADV " />
  <ID161 text="^" lemma="^" tag="^" />
  <ID162 text="^" lemma="^" tag="^" />
  <ID163 text="^" lemma="^" tag="^" />
  <ID164 text="Mélanthios alluma le feu infatigable et apporta du dedans un grand rouleau de suif " lemma="Melanthios allumer le feu infatigable et apporter du dedans un grand rouleau de suif " tag="NAM VER DET:ART NOM ADJ CONJcoord VER DET:ART ADV DET:ART ADJ NOM PRP NOM " />
  <ID165 text="ayant réchauffé l' arc , les jeunes gens l' éprouvèrent , mais ils ne purent le tendre , il s' en fallait de beaucoup " lemma="avoir rechauffer le arc , le jeune gens le eprouver , mais ils ne pouvoir le tendre , il se en falloir de beaucoup " tag="VER VER:pper DET:ART NOM PUN DET:ART ADJ NOM DET:ART VER PUN CONJcoord PRO ADV VER DET:ART ADJ PUN PRO PRO PRP VER PRP ADV " />
  <ID166 text="Restaient encore " lemma="rester encore " tag="VER ADV " />
  <ID167 text="^" lemma="^" tag="^" />
  <ID168 text="Antinoos et " lemma="Antinoos et " tag="NAM CONJcoord " />
  <ID169 text="Eurymachos semblable à un dieu , les principaux des prétendants , car ils étaient de beaucoup les plus courageux " lemma="Eurymachos semblable a un dieu , le principal un pretendant , car ils etre de beaucoup le plus courageux " tag="NAM ADJ PRP DET:ART NOM PUN DET:ART ADJ DET:ART NOM PUN CONJcoord PRO VER PRP ADV DET:ART ADV ADJ " />
  <ID170 text="/ Déjà " lemma="/ deja " tag="PUN ADV " />
  <ID171 text="Eurymachos tourne l' arc dans ses mains , l' exposant , tantôt en un point , tantôt en l' autre , à la chaleur du feu " lemma="Eurymachos tourner le arc dans ses main , le exposer , tantôt en un point , tantôt en le autre , a le chaleur du feu " tag="NAM VER DET:ART NOM PRP DET:ART NOM PUN DET:ART VER PUN ADV PRP DET:ART ADV PUN ADV PRP DET:ART ADJ PUN PRP DET:ART NOM DET:ART NOM " />
  <ID172 text="Mais il ne peut le tendre et son noble cœur en est grandement affligé " lemma="mais il ne pouvoir le tendre et son noble coeur en etre grandement affliger " tag="CONJcoord PRO ADV VER DET:ART ADJ CONJcoord DET:ART ADJ NOM PRP VER ADV VER " />
  <ID173 text="Il gémit et dit ces paroles " lemma="il gemir et dire ces parole " tag="PRO VER CONJcoord VER DET:ART NOM " />
  <ID174 text="/ &quot; Hélas " lemma="/ &quot; helas " tag="PUN PUN EXCL " />
  <ID175 text="je m' afflige et sur moi-même et sur nous tous ; ce n' est pas à cause de ce mariage que je me lamente , bien que j' en sois attristé  il est encore beaucoup d' autres " lemma="je me affliger et sur moi-meme et sur nous tous ; ce ne etre pas a cause de ce mariage que je me lamenter , bien que je en etre attriste  il etre encore beaucoup de autres " tag="PRO PRO VER CONJcoord PRP PRO CONJcoord PRP PRO DET:ART PUN DET:ART ADV VER ADV PRP NOM PRP DET:ART NOM PRO PRO PRO VER PUN ADV PRO PRO PRP VER ADJ  PRO VER ADV ADV PRP PRO " />
  <ID176 text="Achéennes , et dans cette même " lemma="Acheennes , et dans cette meme " tag="NAM PUN CONJcoord PRP DET:ART ADV " />
  <ID177 text="Ithaque entourée par la mer , et dans d' autres villes ; mais bien parce que nous sommes si éloignés de la force du divin " lemma="Ithaque entourer par le mer , et dans de autres ville ; mais bien parce que nous etre si eloigner de le force du divin " tag="NAM VER:pper PRP DET:ART NOM PUN CONJcoord PRP PRP PRO NOM PUN CONJcoord ADV Indef PRO PRO VER CONJsubord VER:pper PRP DET:ART NOM DET:ART ADJ " />
  <ID178 text="Ulysse , que nous n' avons pu tendre son arc  Notre honte sera connue même de ceux qui viendront " lemma="Ulysse , que nous ne avoir pouvoir tendre son arc  notre honte etre connaître meme de ceux qui venir " tag="NAM PUN PRO PRO ADV VER VER ADJ DET:ART NOM  DET:ART NOM VER VER ADV PRP PRO PRO VER " />
  <ID179 text="&quot; / Alors " lemma="&quot; / alors " tag="PUN PUN ADV " />
  <ID180 text="Antinoos , fils d' " lemma="Antinoos , fils de " tag="NAM PUN NOM PRP " />
  <ID181 text="Eupithès , lui dit " lemma="Eupithes , lui dire " tag="NAM PUN PRO VER " />
  <ID182 text="/ &quot; " lemma="/ &quot; " tag="PUN PUN " />
  <ID183 text="Eurymachos , il n' en sera pas ainsi  tu le sais bien toi-même  Aujourd'hui c' est , parmi le peuple , la sainte fête d'  Apollon " lemma="Eurymachos , il ne en etre pas ainsi  tu le savoir bien toi-meme  aujourd'hui ce etre , parmi le peuple , le saint fete de  Apollon " tag="NAM PUN PRO ADV PRP VER ADV ADV  PRO DET:ART VER ADV PRO  ADV DET:ART VER PUN PRP DET:ART NOM PUN DET:ART ADJ NOM PRP  NAM " />
  <ID184 text="comment donc pourrait on tendre l' arc " lemma="comment donc pouvoir on tendre le arc " tag="ADV CONJcoord VER PRO ADJ DET:ART NOM " />
  <ID185 text="Déposons le tranquillement ; quant aux haches , laissons les debout , car je ne pense pas que quelqu'un les enlève , en s' introduisant dans le palais d' " lemma="deposer le tranquillement ; quant aux hache , laisser le debout , car je ne penser pas que quelqu'un le enlever , en se introduire dans le palais de " tag="VER DET:ART ADV PUN NOM DET:ART NOM PUN VER DET:ART ADJ PUN CONJcoord PRO ADV VER ADV PRO PRO DET:ART VER PUN PRP PRO VER PRP DET:ART NOM PRP " />
  <ID186 text="Ulysse , fils de " lemma="Ulysse , fils de " tag="NAM PUN NOM PRP " />
  <ID187 text="Laërte " lemma="Laërte " tag="NAM " />
  <ID188 text="Allons , que l' échanson remplisse nos coupes , afin que nous fassions une libation en déposant l' arc recourbé " lemma="aller , que le echanson remplir nos coupe , afin que nous faire un libation en deposer le arc recourbe " tag="VER PUN PRO DET:ART NOM VER DET:ART NOM PUN PRP PRO PRO VER DET:ART NOM PRP VER DET:ART NOM ADJ " />
  <ID189 text="Dès l' aurore , vous ordonnerez à " lemma="des le aurore , vous ordonnerez a " tag="PRP DET:ART NOM PUN PRO Indef PRP " />
  <ID190 text="Mélanthios , le chevrier , de conduire les chèvres qui l' emportent de beaucoup entre tous les troupeaux , afin qu' offrant leurs cuisses à " lemma="Melanthios , le chevrier , de conduire le chevre qui le emporter de beaucoup entre tous le troupeau , afin que offrir leurs cuisse a " tag="NAM PUN DET:ART NOM PUN PRP VER DET:ART NOM PRO DET:ART VER PRP ADV PRP DET:ART DET:ART NOM PUN PRP PRO VER DET:ART NOM PRP " />
  <ID191 text="Apollon , le célèbre archer , nous essayions l' arc et terminions la lutte " lemma="Apollon , le celebre archer , nous essayer le arc et terminer le lutte " tag="NAM PUN DET:ART ADJ NOM PUN PRO VER DET:ART NOM CONJcoord VER DET:ART NOM " />
  <ID192 text="&quot; / Ainsi parla " lemma="&quot; / ainsi parler " tag="PUN PUN ADV VER " />
  <ID193 text="Antinoos et l' avis leur plut " lemma="Antinoos et le avis leurs plaire " tag="NAM CONJcoord DET:ART NOM DET:ART VER " />
  <ID194 text="Les hérauts leur versèrent de l' eau sur les mains ; les jeunes gens remplirent les cratères de boisson , et la distribuèrent entre tous en la versant dans les coupes " lemma="le heraut leurs verser de le eau sur le main ; le jeune gens remplir le cratere de boisson , et le distribuer entre tous en le versant dans le coupe " tag="DET:ART NOM DET:ART VER PRP DET:ART NOM PRP DET:ART NOM PUN DET:ART ADJ NOM VER DET:ART NOM PRP NOM PUN CONJcoord DET:ART VER PRP DET:ART PRP DET:ART NOM PRP DET:ART NOM " />
  <ID195 text="Lorsqu' ils eurent donc fait leurs libations et bu autant que leur cœur le désirait , alors , méditant des ruses , le sage " lemma="lorsque ils avoir donc faire leurs libation et boire autant que leurs coeur le desirer , alors , mediter un ruse , le sage " tag="CONJsubord PRO VER CONJcoord VER DET:ART NOM CONJcoord VER ADV PRO DET:ART NOM DET:ART VER PUN ADV PUN VER DET:ART NOM PUN DET:ART ADJ " />
  <ID196 text="Ulysse leur dit " lemma="Ulysse leurs dire " tag="NAM DET:ART VER " />
  <ID197 text="/ &quot; Écoutez moi , illustres rois prétendants ; mais j' adresse surtout ma prière à " lemma="/ &quot; ecouter moi , illustre roi pretendant ; mais je adresse surtout ma priere a " tag="PUN PUN VER PRO PUN ADJ NOM NOM PUN CONJcoord PRO NOM ADV DET:ART NOM PRP " />
  <ID198 text="Eurymachos et à " lemma="Eurymachos et a " tag="NAM CONJcoord PRP " />
  <ID199 text="Antinoos , car ce dernier a parlé comme il faut en disant qu' il fallait maintenant laisser l' arc et remettre la chose aux dieux ; que demain , le dieu donnerait la force à qui il le voudrait " lemma="Antinoos , car ce dernier avoir parler comme il falloir en dire que il falloir maintenant laisser le arc et remettre le chose aux dieu ; que demain , le dieu donner le force a qui il le vouloir " tag="NAM PUN CONJcoord DET:ART ADJ VER VER CONJsubord PRO VER PRP VER PRO PRO VER ADV VER DET:ART NOM CONJcoord VER DET:ART NOM DET:ART NOM PUN PRO ADV PUN DET:ART NOM VER DET:ART NOM PRP PRO PRO DET:ART VER " />
  <ID200 text="Mais donnez moi l' arc bien poli , afin qu' après vous , j' éprouve mes bras et ma force , que je sache si ma vigueur est encore telle qu' elle était autrefois dans mes membres souples , ou si elle m' a abandonné par suite de " lemma="mais donner moi le arc bien poli , afin que apres vous , je eprouver mes bras et ma force , que je savoir si ma vigueur etre encore telle que elle etre autrefois dans mes membre souple , ou si elle me avoir abandonner par suite de " tag="CONJcoord VER PRO DET:ART NOM ADV ADJ PUN PRP PRO PRP PRO PUN PRO VER DET:ART NOM CONJcoord DET:ART NOM PUN PRO PRO VER CONJsubord DET:ART NOM VER ADV DET:ART PRO PRO VER ADV PRP DET:ART NOM ADJ PUN PRO CONJsubord PRO PRO VER VER:pper PRP NOM PRP " />
  <ID201 text="" lemma="" tag="" />
  <ID202 text="&quot; / Il parla ainsi et tous , mais principalement " lemma="&quot; / il parler ainsi et tous , mais principalement " tag="PUN PUN PRO VER ADV CONJcoord DET:ART PUN CONJcoord ADV " />
  <ID203 text="Antinoos , l' accablèrent d' insolences , craignant qu' il ne tendît l' arc bien poli " lemma="Antinoos , le accabler de insolence , craindre que il ne tendre le arc bien poli " tag="NAM PUN DET:ART VER PRP NOM PUN VER PRO PRO ADV ADJ DET:ART NOM ADV ADJ " />
  <ID204 text="^" lemma="^" tag="^" />
  <ID205 text="^" lemma="^" tag="^" />
  <ID206 text="^" lemma="^" tag="^" />
  <ID207 text="^" lemma="^" tag="^" />
  <ID208 text="^" lemma="^" tag="^" />
  <ID209 text="^" lemma="^" tag="^" />
  <ID210 text="^" lemma="^" tag="^" />
  <ID211 text="^" lemma="^" tag="^" />
  <ID212 text="^" lemma="^" tag="^" />
  <ID213 text="/ Alors la sage " lemma="/ alors le sage " tag="PUN ADV DET:ART ADJ " />
  <ID214 text="^" lemma="^" tag="^" />
  <ID215 text="^" lemma="^" tag="^" />
  <ID216 text="^" lemma="^" tag="^" />
  <ID217 text="^" lemma="^" tag="^" />
  <ID218 text="^" lemma="^" tag="^" />
  <ID219 text="Pénélope dit " lemma="Penelope dire " tag="NAM VER " />
  <ID220 text="/ &quot; " lemma="/ &quot; " tag="PUN PUN " />
  <ID221 text="Antinoos , il n' est ni beau , ni juste d' injurier les hôtes de " lemma="Antinoos , il ne etre ni beau , ni juste de injurier le hôte de " tag="NAM PUN PRO ADV VER CONJcoord ADJ PUN CONJcoord ADJ PRP VER DET:ART NOM PRP " />
  <ID222 text="Télémaque , quel que soit celui qui se présente dans sa maison " lemma="Telemaque , quel que etre celui qui se presenter dans sa maison " tag="NAM PUN DETinter PRO VER PRO PRO PRO VER PRP DET:ART NOM " />
  <ID223 text="Crois tu que si l' étranger , confiant dans ses bras et dans sa force , tend le grand arc d' " lemma="croire tu que si le etranger , confiant dans ses bras et dans sa force , tendre le grand arc de " tag="VER PRO PRO CONJsubord DET:ART NOM PUN ADJ PRP DET:ART NOM CONJcoord PRP DET:ART NOM PUN ADJ DET:ART ADJ NOM PRP " />
  <ID224 text="Ulysse , il me conduira chez lui et me fera son épouse  Mais lui-même n' espère pas cela dans sa poitrine " lemma="Ulysse , il me conduire chez lui et me faire son epoux  mais lui-meme ne esperer pas cela dans sa poitrine " tag="NAM PUN PRO PRO VER PRP PRO CONJcoord PRO VER DET:ART NOM  CONJcoord PRO ADV VER ADV PRO PRP DET:ART NOM " />
  <ID225 text="Que donc , au milieu du festin , aucun de vous ne s' afflige dans son cœur à cause de cela , car il n' y a rien de semblable à cela " lemma="que donc , au milieu du festin , aucun de vous ne se affliger dans son coeur a cause de cela , car il ne y avoir rien de semblable a cela " tag="PRO CONJcoord PUN DET:ART NOM DET:ART NOM PUN DET:ART PRP PRO ADV PRO VER PRP DET:ART NOM PRP NOM PRP PRO PUN CONJcoord PRO ADV PRO VER PRO PRP ADJ PRP PRO " />
  <ID226 text="&quot; Alors " lemma="&quot; alors " tag="PUN ADV " />
  <ID227 text="Eurymachos , fils de " lemma="Eurymachos , fils de " tag="NAM PUN NOM PRP " />
  <ID228 text="Polybos , lui dit " lemma="Polybos , lui dire " tag="NAM PUN PRO VER " />
  <ID229 text="/ &quot; Fille d' " lemma="/ &quot; fille de " tag="PUN PUN NOM PRP " />
  <ID230 text="Icare , sage " lemma="Icare , sage " tag="NAM PUN ADJ " />
  <ID231 text="Pénélope , nous ne pensons pas qu' il te conduise chez lui  c' est invraisemblable ; mais nous craignons les dires des hommes et des femmes  Un jour quelqu'un des plus vils entre les " lemma="Penelope , nous ne penser pas que il te conduire chez lui  ce etre invraisemblable ; mais nous craindre le dire un homme et un femme  un jour quelqu'un un plus vil entre le " tag="NAM PUN PRO ADV VER ADV PRO PRO PRO VER PRP PRO  DET:ART VER ADJ PUN CONJcoord PRO VER DET:ART VER DET:ART NOM CONJcoord DET:ART NOM  DET:ART NOM PRO DET:ART ADV ADJ PRP DET:ART " />
  <ID232 text="Achéens pourrait dire " lemma="Acheens pouvoir dire " tag="NAM VER VER " />
  <ID233 text="des hommes qui ne le valaient pas se fiançaient à la femme d' un héros irréprochable ; ils ne parvinrent pas à tendre son arc bien poli ; mais un autre homme , un mendiant vagabond , étant survenu , tendit facilement l' arc et lança la flèche à travers le fer " lemma="un homme qui ne le valoir pas se fiançaient a le femme de un heros irreprochable ; ils ne parvenir pas a tendre son arc bien poli ; mais un autre homme , un mendiant vagabond , etre survenir , tendre facilement le arc et lancer le fleche a travers le fer " tag="DET:ART NOM PRO ADV DET:ART VER ADV PRO Indef PRP DET:ART NOM PRP DET:ART NOM ADJ PUN PRO ADV VER ADV PRP ADJ DET:ART NOM ADV ADJ PUN CONJcoord DET:ART ADJ NOM PUN DET:ART NOM NOM PUN VER VER PUN ADJ ADV DET:ART NOM CONJcoord VER DET:ART NOM PRP NOM DET:ART NOM " />
  <ID234 text="Voilà ce que l' on dirait et cela serait déshonorant pour nous " lemma="voila ce que le on dire et cela etre deshonorant pour nous " tag="PRP DET:ART PRO DET:ART PRO VER CONJcoord PRO VER ADJ PRP PRO " />
  <ID235 text="/ La sage " lemma="/ le sage " tag="PUN DET:ART ADJ " />
  <ID236 text="Pénélope lui répondit " lemma="Penelope lui repondre " tag="NAM PRO VER " />
  <ID237 text="/ &quot; " lemma="/ &quot; " tag="PUN PUN " />
  <ID238 text="Eurymachos , ils n' acquièrent pas une bonne renommée parmi le peuple , ceux qui ne respectent pas la maison d' un homme noble et qui mangent son bien ; pourquoi donc considérez vous ceci comme déshonorant " lemma="Eurymachos , ils ne acquerir pas un bon renommee parmi le peuple , ceux qui ne respecter pas le maison de un homme noble et qui manger son bien ; pourquoi donc considerer vous ceci comme deshonorant " tag="NAM PUN PRO ADV VER ADV DET:ART ADJ NOM PRP DET:ART NOM PUN PRO PRO ADV VER ADV DET:ART NOM PRP DET:ART NOM ADJ CONJcoord PRO VER DET:ART ADV PUN ADV CONJcoord VER PRO PRO CONJsubord ADJ " />
  <ID239 text="^" lemma="^" tag="^" />
  <ID240 text="Cet étranger est grand et bien bâti ; il se glorifie d' être le fils d' un père de noble race ; donnez lui donc l' arc bien poli , afin que nous voyions " lemma="cet etranger etre grand et bien batir ; il se glorifier de etre le fils de un pere de noble race ; donner lui donc le arc bien poli , afin que nous voir " tag="DET:ART NOM VER ADJ CONJcoord ADV VER PUN PRO PRO VER PRP VER DET:ART NOM PRP DET:ART NOM PRP ADJ NOM PUN VER PRO CONJcoord DET:ART NOM ADV ADJ PUN PRP PRO PRO VER " />
  <ID241 text="Car voici ce que je dirai , et cela sera accompli " lemma="car voici ce que je dire , et cela etre accomplir " tag="CONJcoord PRP DET:ART PRO PRO VER PUN CONJcoord PRO VER VER " />
  <ID242 text="^" lemma="^" tag="^" />
  <ID243 text="s' il le tend , je l' habillerai de beaux vêtements , d' un manteau et d' une tunique ; je lui donnerai un javelot aigu , défense contre les chiens et les hommes et une épée à deux tranchants ; je lui donnerai des sandales à mettre à ses pieds et lui fournirai les moyens d' aller où son cœur le désire " lemma="se il le tendre , je le habiller de beau vetement , de un manteau et de un tunique ; je lui donner un javelot aigu , defense contre le chien et le homme et un epee a deux tranchant ; je lui donner un sandale a mettre a ses pied et lui fournir le moyen de aller ou son coeur le desirer " tag="PRO PRO DET:ART ADJ PUN PRO DET:ART VER PRP ADJ NOM PUN PRP DET:ART NOM CONJcoord PRP DET:ART NOM PUN PRO PRO VER DET:ART NOM ADJ PUN NOM PRP DET:ART NOM CONJcoord DET:ART NOM CONJcoord DET:ART NOM PRP NUM ADJ PUN PRO PRO VER DET:ART NOM PRP VER PRP DET:ART NOM CONJcoord PRO VER DET:ART NOM PRP VER PRO DET:ART NOM DET:ART VER " />
  <ID244 text="/ Le sage " lemma="/ le sage " tag="PUN DET:ART ADJ " />
  <ID245 text="Télémaque lui répondit " lemma="Telemaque lui repondre " tag="NAM PRO VER " />
  <ID246 text="/ &quot; Ma mère , de tous les " lemma="/ &quot; ma mere , de tous le " tag="PUN PUN DET:ART NOM PUN PRP DET:ART DET:ART " />
  <ID247 text="Grecs , personne n' a le droit autant que moi de donner ou de refuser l' arc à qui je le veux , ni de ceux qui dominent dans la pierreuse " lemma="Grecs , personne ne avoir le droit autant que moi de donner ou de refuser le arc a qui je le vouloir , ni de ceux qui dominer dans le pierreux " tag="NAM PUN PRO ADV VER DET:ART NOM ADV PRO PRO PRP VER PRO PRP VER DET:ART NOM PRP PRO PRO DET:ART VER PUN CONJcoord PRP PRO PRO VER PRP DET:ART ADJ " />
  <ID248 text="Ithaque , ni de ceux qui habitent l'  Èlide , nourricière de chevaux " lemma="Ithaque , ni de ceux qui habiter le  Èlide , nourricier de cheval " tag="NAM PUN CONJcoord PRP PRO PRO VER DET:ART  NAM PUN ADJ PRP NOM " />
  <ID249 text="Aucun d' entre eux ne me forcera à le livrer malgré moi et si je le veux , je puis donner tout à fait à cet étranger l' arc à emporter  Mais va dans la maison et occupe toi de tes propres affaires , de ton métier , de tes fuseaux et donne des ordres à tes servantes " lemma="aucun de entre eux ne me forcer a le livrer malgre moi et si je le vouloir , je puis donner tout a faire a cet etranger le arc a emporter  mais aller dans le maison et occuper toi de tes propre affaire , de ton metier , de tes fuseau et donner un ordre a tes servante " tag="DET:ART PRP PRP PRO ADV PRO VER PRP DET:ART VER PRP PRO CONJcoord CONJsubord PRO DET:ART VER PUN PRO ADV VER DET:ART PRP VER PRP DET:ART NOM DET:ART NOM PRP VER  CONJcoord VER PRP DET:ART NOM CONJcoord VER PRO PRP DET:ART ADJ NOM PUN PRP DET:ART NOM PUN PRP DET:ART NOM CONJcoord VER DET:ART NOM PRP DET:ART NOM " />
  <ID250 text="L' arc est l' affaire de tous les hommes et de moi principalement  à moi appartient l' autorité dans la maison " lemma="le arc etre le affaire de tous le homme et de moi principalement  a moi appartenir le autorite dans le maison " tag="DET:ART NOM VER DET:ART NOM PRP DET:ART DET:ART NOM CONJcoord PRP PRO ADV  PRP PRO VER DET:ART NOM PRP DET:ART NOM " />
  <ID251 text="&quot; / " lemma="&quot; / " tag="PUN PUN " />
  <ID252 text="Pénélope , étonnée , s' en retourna chez elle , car elle avait mis dans son esprit l' avis intelligent de son enfant " lemma="Penelope , etonner , se en retourner chez elle , car elle avoir mettre dans son esprit le avis intelligent de son enfant " tag="NAM PUN VER:pper PUN PRO PRP VER PRP PRO PUN CONJcoord PRO VER VER PRP DET:ART NOM DET:ART NOM ADJ PRP DET:ART NOM " />
  <ID253 text="Étant montée à l' étage avec ses suivantes , elle pleura ensuite " lemma="etre montee a le etage avec ses suivant , elle pleurer ensuite " tag="VER NOM PRP DET:ART NOM PRP DET:ART ADJ PUN PRO VER ADV " />
  <ID254 text="Ulysse , son cher époux , jusqu' à ce qu' " lemma="Ulysse , son cher epoux , jusque a ce que " tag="NAM PUN DET:ART ADJ NOM PUN PRP PRP DET:ART PRO " />
  <ID255 text="^" lemma="^" tag="^" />
  <ID256 text="^" lemma="^" tag="^" />
  <ID257 text="Athéné , à la face de hibou , lui jetât sur les paupières un doux sommeil " lemma="Athene , a le face de hibou , lui jeter sur le paupiere un doux sommeil " tag="NAM PUN PRP DET:ART NOM PRP NOM PUN PRO VER PRP DET:ART NOM DET:ART ADJ NOM " />
  <ID258 text="^" lemma="^" tag="^" />
  <ID259 text="^" lemma="^" tag="^" />
  <ID260 text="^" lemma="^" tag="^" />
  <ID261 text="/ Cependant le divin porcher prit l' arc recourbé " lemma="/ cependant le divin porcher prendre le arc recourbe " tag="PUN ADV DET:ART ADJ NOM VER DET:ART NOM ADJ " />
  <ID262 text="^" lemma="^" tag="^" />
  <ID263 text="tous les prétendants alors l' accablèrent de menaces et saisi de crainte , il déposa l' arc à l' endroit même où il se trouvait " lemma="tous le pretendant alors le accabler de menace et saisir de crainte , il deposer le arc a le endroit meme ou il se trouver " tag="DET:ART DET:ART NOM ADV DET:ART VER PRP NOM CONJcoord VER PRP NOM PUN PRO VER DET:ART NOM PRP DET:ART NOM ADV PRO PRO PRO VER " />
  <ID264 text="Mais d' un autre côté , " lemma="mais de un autre côte , " tag="CONJcoord PRP DET:ART ADJ NOM PUN " />
  <ID265 text="Télémaque lui cria d' un ton menaçant " lemma="Telemaque lui crier de un ton menaçant " tag="NAM PRO VER PRP DET:ART DET:ART ADJ " />
  <ID266 text="^" lemma="^" tag="^" />
  <ID267 text="/ &quot; Père , porte l' arc plus loin ; on ne peut pas bien obéir à tout le monde " lemma="/ &quot; pere , porte le arc plus loin ; on ne pouvoir pas bien obeir a tout le monde " tag="PUN PUN NOM PUN NOM DET:ART NOM ADV ADV PUN PRO ADV VER ADV ADV VER PRP DET:ART DET:ART NOM " />
  <ID268 text="Prends garde que , bien que plus jeune que toi , je ne te chasse aux champs à coups de pierres , car je te suis supérieur en force " lemma="prendre garde que , bien que plus jeune que toi , je ne te chasse aux champ a coup de pierre , car je te etre superieur en force " tag="VER NOM PRO PUN ADV PRO ADV ADJ PRO PRO PUN PRO ADV PRO NOM DET:ART NOM PRP NOM PRP NOM PUN CONJcoord PRO PRO VER ADJ PRP NOM " />
  <ID269 text="Que ne suis je / supérieur en force à tous les prétendants qui se trouvent dans la maison , je les ferais bientôt sortir d' une manière funèbre de notre maison , où ils machinent de mauvais desseins " lemma="que ne etre je / superieur en force a tous le pretendant qui se trouver dans le maison , je le faire bientôt sortir de un maniere funebre de notre maison , ou ils machinent de mauvais dessein " tag="PRO ADV VER PRO PUN ADJ PRP NOM PRP DET:ART DET:ART NOM PRO PRO VER PRP DET:ART NOM PUN PRO DET:ART VER ADV VER PRP DET:ART NOM ADJ PRP DET:ART NOM PUN PRO PRO Indef PRP ADJ NOM " />
  <ID270 text="&quot; / Il parla ainsi et tous les prétendants rirent agréablement de lui et oublièrent leur lourde colère contre " lemma="&quot; / il parler ainsi et tous le pretendant rire agreablement de lui et oublier leurs lourd colere contre " tag="PUN PUN PRO VER ADV CONJcoord DET:ART DET:ART NOM VER ADV PRP PRO CONJcoord VER DET:ART ADJ NOM PRP " />
  <ID271 text="Télémaque " lemma="Telemaque " tag="NAM " />
  <ID272 text="Le porcher , ayant porté l' arc à travers la maison , s' arrêta devant " lemma="le porcher , avoir porter le arc a travers le maison , se arreter devant " tag="DET:ART NOM PUN VER VER:pper DET:ART NOM PRP NOM DET:ART NOM PUN PRO VER PRP " />
  <ID273 text="Ulysse à l' esprit éclairé et le lui remit dans les mains " lemma="Ulysse a le esprit eclairer et le lui remettre dans le main " tag="NAM PRP DET:ART NOM VER:pper CONJcoord DET:ART PRO VER PRP DET:ART NOM " />
  <ID274 text="Celui ci se mit à manier l' arc , le retournant de tous côtés , l' éprouvant ici et là , examinant si les vers n' avaient pas rongé la corne pendant son absence " lemma="celui ci se mettre a manier le arc , le retourner de tous côte , le eprouver ici et la , examiner si le vers ne avoir pas ronger le corne pendant son absence " tag="PRO ADV PRO VER PRP VER DET:ART NOM PUN DET:ART VER PRP DET:ART NOM PUN DET:ART VER ADV CONJcoord ADV PUN VER CONJsubord DET:ART PRP ADV VER ADV VER:pper DET:ART NOM PRP DET:ART NOM " />
  <ID275 text="Le voyant , ils se disaient les uns aux autres " lemma="le voir , ils se dire le uns aux autres " tag="DET:ART VER PUN PRO PRO VER DET:ART PRO DET:ART PRO " />
  <ID276 text="/ Ce doit être quelque admirateur et voleur d' arcs ; ou bien peut-être en a t il de tout à fait pareils dans sa maison ; ou il veut peut-être en fabriquer ; comme il le tourne et retourne dans ses mains , ce vagabond adroit au mal " lemma="/ ce devoir etre quelque admirateur et voleur de arc ; ou bien peut-etre en avoir t il de tout a faire pareil dans sa maison ; ou il vouloir peut-etre en fabriquer ; comme il le tourner et retourner dans ses main , ce vagabond adroit au mal " tag="PUN DET:ART VER VER DET:ART NOM CONJcoord NOM PRP NOM PUN PRO ADV ADV PRP VER Indef PRO PRP DET:ART PRP VER ADJ PRP DET:ART NOM PUN PRO PRO VER ADV PRP VER PUN CONJsubord PRO DET:ART VER CONJcoord VER PRP DET:ART NOM PUN DET:ART NOM ADJ DET:ART ADV " />
  <ID277 text="^" lemma="^" tag="^" />
  <ID278 text="&gt; / D' autres des jeunes présomptueux disaient " lemma="&gt; / de autres un jeune presomptueux dire " tag="Indef PUN PRP PRO DET:ART ADJ ADJ VER " />
  <ID279 text="^" lemma="^" tag="^" />
  <ID280 text="^" lemma="^" tag="^" />
  <ID281 text="^" lemma="^" tag="^" />
  <ID282 text="&quot; puisse t il n' avoir jamais plus de réussite qu' il n' en aura en voulant tendre l' arc " lemma="&quot; pouvoir t il ne avoir jamais plus de reussite que il ne en avoir en vouloir tendre le arc " tag="PUN VER Indef PRO ADV VER ADV ADV PRP NOM PRO PRO ADV PRP VER PRP VER ADJ DET:ART NOM " />
  <ID283 text="^" lemma="^" tag="^" />
  <ID284 text="^" lemma="^" tag="^" />
  <ID285 text="^" lemma="^" tag="^" />
  <ID286 text="^" lemma="^" tag="^" />
  <ID287 text="^" lemma="^" tag="^" />
  <ID288 text="^" lemma="^" tag="^" />
  <ID289 text="&quot; / Ainsi parlaient les prétendants ; cependant le sage " lemma="&quot; / ainsi parler le pretendant ; cependant le sage " tag="PUN PUN ADV VER DET:ART NOM PUN ADV DET:ART ADJ " />
  <ID290 text="Ulysse , après qu' il eut palpé et regardé l' arc de tous côtés , de même qu' un homme qui connaît bien la lyre et le chant tend facilement une corde sur une nouvelle cheville , en saisissant des deux côtés le boyau de brebis bien tressé , ainsi , sans précipitation , " lemma="Ulysse , apres que il avoir palper et regarder le arc de tous côte , de meme que un homme qui connaître bien le lyre et le chant tendre facilement un corde sur un nouvelle cheville , en saisir un deux côte le boyau de brebis bien tresser , ainsi , sans precipitation , " tag="NAM PUN PRP PRO PRO VER VER:pper CONJcoord VER:pper DET:ART NOM PRP DET:ART NOM PUN PRP ADV PRO DET:ART NOM PRO VER ADV DET:ART NOM CONJcoord DET:ART NOM ADJ ADV DET:ART NOM PRP DET:ART ADJ NOM PUN PRP VER DET:ART NUM NOM DET:ART NOM PRP NOM ADV VER:pper PUN ADV PUN PRP NOM PUN " />
  <ID291 text="Ulysse tendit le grand arc " lemma="Ulysse tendre le grand arc " tag="NAM ADJ DET:ART ADJ NOM " />
  <ID292 text="Puis , le prenant de la main droite , il éprouva la corde " lemma="puis , le prendre de le main droite , il eprouver le corde " tag="ADV PUN DET:ART VER PRP DET:ART NOM NOM PUN PRO VER DET:ART NOM " />
  <ID293 text="elle rendit un beau son , semblable à la voix d' une hirondelle " lemma="elle rendre un beau son , semblable a le voix de un hirondelle " tag="PRO VER DET:ART ADJ DET:ART PUN ADJ PRP DET:ART NOM PRP DET:ART NOM " />
  <ID294 text="/ Un grand trouble saisit les prétendants et tous tressaillirent ; cependant " lemma="/ un grand trouble saisir le pretendant et tous tressaillir ; cependant " tag="PUN DET:ART ADJ NOM VER DET:ART NOM CONJcoord DET:ART VER PUN ADV " />
  <ID295 text="Zeus envoya comme présage un grand coup de tonnerre " lemma="Zeus envoyer comme presage un grand coup de tonnerre " tag="NAM VER CONJsubord NOM DET:ART ADJ NOM PRP NOM " />
  <ID296 text="Alors le divin " lemma="alors le divin " tag="ADV DET:ART ADJ " />
  <ID297 text="Ulysse se réjouit de ce que le fils de " lemma="Ulysse se rejouir de ce que le fils de " tag="NAM PRO VER PRP DET:ART PRO DET:ART NOM PRP " />
  <ID298 text="Cronos aux desseins tortueux lui envoyait un présage " lemma="Cronos aux dessein tortueux lui envoyer un presage " tag="NAM DET:ART NOM ADJ PRO VER DET:ART NOM " />
  <ID299 text="Il prit la flèche rapide qui était étendue devant lui sur la table  les autres gisaient au fond du carquois creux et les " lemma="il prendre le fleche rapide qui etre etendue devant lui sur le table  le autres gesir au fond du carquois creux et le " tag="PRO VER DET:ART NOM ADJ PRO VER NOM PRP PRO PRP DET:ART NOM  DET:ART PRO VER DET:ART NOM DET:ART NOM NOM CONJcoord DET:ART " />
  <ID300 text="Achéens devaient bientôt les éprouver  La prenant dans sa main , il tira à la fois la corde et la coche de la flèche , et du siège où il était assis , visant en face de lui , il lança le trait " lemma="Acheens devoir bientôt le eprouver  le prendre dans sa main , il tirer a le fois le corde et le coche de le fleche , et du siege ou il etre asseoir , viser en face de lui , il lancer le trait " tag="NAM VER ADV DET:ART VER  DET:ART VER PRP DET:ART NOM PUN PRO VER PRP DET:ART NOM DET:ART NOM CONJcoord DET:ART NOM PRP DET:ART NOM PUN CONJcoord DET:ART NOM PRO PRO VER VER PUN VER PRP NOM PRP PRO PUN PRO VER DET:ART NOM " />
  <ID301 text="De la première ouverture , la flèche traversa toutes les haches sans en manquer une et alla tout droit jusqu' à la porte du fond  Cependant " lemma="de le premier ouverture , le fleche traverser tout le hache sans en manquer un et aller tout droit jusque a le porte du fond  cependant " tag="PRP DET:ART ADJ NOM PUN DET:ART NOM VER DET:ART DET:ART NOM PRP PRP VER:pper DET:ART CONJcoord VER DET:ART NOM PRP PRP DET:ART NOM DET:ART NOM  ADV " />
  <ID302 text="Ulysse dit à " lemma="Ulysse dire a " tag="NAM VER PRP " />
  <ID303 text="Télémaque " lemma="Telemaque " tag="NAM " />
  <ID304 text="/ &quot; " lemma="/ &quot; " tag="PUN PUN " />
  <ID305 text="Télémaque , l' hôte qui est assis dans ton palais ne te fais pas honte  il n' a pas manqué le but et il ne s' est pas fatigué longtemps à tendre l' arc " lemma="Telemaque , le hôte qui etre asseoir dans ton palais ne te faire pas honte  il ne avoir pas manquer le but et il ne se etre pas fatigue longtemps a tendre le arc " tag="NAM PUN DET:ART NOM PRO VER VER PRP DET:ART NOM ADV PRO VER ADV NOM  PRO ADV VER ADV VER:pper DET:ART NOM CONJcoord PRO ADV PRO VER ADV ADJ ADV PRP ADJ DET:ART NOM " />
  <ID306 text="J' ai encore ma force tout entière et je ne suis pas ce que les prétendants me qualifient en m' injuriant " lemma="je avoir encore ma force tout entier et je ne etre pas ce que le pretendant me qualifier en me injurier " tag="PRO VER ADV DET:ART NOM DET:ART ADJ CONJcoord PRO ADV VER ADV DET:ART PRO DET:ART NOM PRO VER PRP PRO VER " />
  <ID307 text="Maintenant il est temps de préparer aux " lemma="maintenant il etre temps de preparer aux " tag="ADV PRO VER NOM PRP VER DET:ART " />
  <ID308 text="Achéens un souper en plein jour , et ensuite de les réjouir autrement par la danse et la lyre , qui sont les accompagnements du festin " lemma="Acheens un souper en plein jour , et ensuite de le rejouir autrement par le danse et le lyre , qui etre le accompagnement du festin " tag="NAM DET:ART NOM PRP ADJ NOM PUN CONJcoord ADV PRP DET:ART VER ADV PRP DET:ART NOM CONJcoord DET:ART NOM PUN PRO VER DET:ART NOM DET:ART NOM " />
  <ID309 text="&quot; / Il dit et fit un signe de ses sourcils " lemma="&quot; / il dire et faire un signe de ses sourcil " tag="PUN PUN PRO VER CONJcoord VER DET:ART NOM PRP DET:ART NOM " />
  <ID310 text="" lemma="" tag="" />
  <ID311 text="Télémaque ceignit son épée tranchante , prit en main sa lance , et armé de l' airain étincelant , se tint debout près du fauteuil de son père " lemma="Telemaque ceindre son epee tranchant , prendre en main sa lancer , et armer de le airain etincelant , se tenir debout pres du fauteuil de son pere " tag="NAM VER DET:ART NOM ADJ PUN VER PRP NOM DET:ART VER PUN CONJcoord VER:pper PRP DET:ART NOM ADJ PUN PRO VER ADJ PRP DET:ART NOM PRP DET:ART NOM " />
</file>
